[{"Country":"tv","AccentCity":"Asau"},{"Country":"tv","AccentCity":"Funafuti"},{"Country":"tv","AccentCity":"Fongafale"},{"Country":"tv","AccentCity":"Kulia"},{"Country":"tv","AccentCity":"Lolua"},{"Country":"tv","AccentCity":"Matagi"},{"Country":"tv","AccentCity":"Muli"},{"Country":"tv","AccentCity":"Polufale"},{"Country":"tv","AccentCity":"Potufale"},{"Country":"tv","AccentCity":"Saniuta"},{"Country":"tv","AccentCity":"Tanrake"},{"Country":"tv","AccentCity":"Tapotali"},{"Country":"tv","AccentCity":"Tonga"},{"Country":"tv","AccentCity":"Vaitupu"}]